tcut_to_qastle/__init__.py
tcut_to_qastle/translate.py
tcut_to_qastle-0.7.dist-info/LICENSE
tcut_to_qastle-0.7.dist-info/METADATA
tcut_to_qastle-0.7.dist-info/WHEEL
tcut_to_qastle-0.7.dist-info/top_level.txt
tcut_to_qastle-0.7.dist-info/RECORD
