Metadata-Version: 2.1
Name: tcut-to-qastle
Version: 0.7
Summary: TCut selection for ROOT TTree to Qastle wrapper for ServiceX xAOD and Uproot transformer
Home-page: https://github.com/ssl-hep/TCutToQastleWrapper
Author: KyungEon Choi (UT Austin)
Author-email: kyungeonchoi@utexas.edu
License: BSD 3-clause
Platform: Any
Classifier: Development Status :: 3 - Alpha
Classifier: Intended Audience :: Developers
Classifier: Intended Audience :: Information Technology
Classifier: Intended Audience :: Science/Research
Classifier: Programming Language :: Python
Classifier: Topic :: Scientific/Engineering :: Physics
Classifier: Topic :: Software Development
Classifier: Topic :: Utilities
License-File: LICENSE
Requires-Dist: qastle (>=0.5)
